{
  "journeys": [
    {
      "id": "ai",
      "title": "(Gen)AI Path",
      "booths": [
        {"id": "cx01", "type": "highlight"},
        {"id": "cx02", "type": "highlight"},
        {"id": "cx03", "type": "highlight"},
        {"id": "cx04", "type": "highlight"},
        {"id": "cx05", "type": "highlight"},
        {"id": "cx06", "type": "highlight"},
        {"id": "cx07", "type": "highlight"},
        {"id": "cx08", "type": "highlight"},
        {"id": "cx09", "type": "highlight"},
        {"id": "cs05", "type": "highlight"},
        {"id": "te02.1", "type": "highlight"},
        {"id": "te02.2", "type": "highlight"},
        {"id": "te02.3", "type": "highlight"},
        {"id": "te02.4", "type": "highlight"},
        {"id": "te05", "type": "highlight"},
        {"id": "te06", "type": "highlight"},
        {"id": "te07", "type": "highlight"},
        {"id": "te09", "type": "highlight"},
        {"id": "te10", "type": "highlight"},
        {"id": "te12", "type": "highlight"},
        {"id": "te14", "type": "highlight"},
        {"id": "te15", "type": "highlight"},
        {"id": "pe01", "type": "highlight"},
        {"id": "pe02", "type": "highlight"},
        {"id": "pe03", "type": "highlight"},
        {"id": "pe05", "type": "highlight"},
        {"id": "pe06", "type": "highlight"},
        {"id": "pe08", "type": "highlight"},
        {"id": "pe13", "type": "highlight"},
        {"id": "pe14", "type": "highlight"},
        {"id": "op01", "type": "highlight"},
        {"id": "op02", "type": "highlight"},
        {"id": "op03", "type": "highlight"},
        {"id": "op04", "type": "highlight"},
        {"id": "op05", "type": "highlight"},
        {"id": "op06", "type": "highlight"},
        {"id": "op07", "type": "highlight"},
        {"id": "op08", "type": "highlight"},
        {"id": "op09", "type": "highlight"},
        {"id": "op10", "type": "highlight"},
        {"id": "op12", "type": "highlight"},
        {"id": "op13", "type": "highlight"},
        {"id": "op14", "type": "highlight"}
      ]
    },
    {
      "id": "consumer",
      "title": "Consumer Products & Retail",
      "booths": [
        {"id": "cx01", "type": "highlight"},
        {"id": "cx02", "type": "highlight"},
        {"id": "cx05", "type": "highlight"},
        {"id": "cx06", "type": "highlight"},
        {"id": "te04", "type": "highlight"},
        {"id": "te06", "type": "highlight"},
        {"id": "pe04", "type": "highlight"},
        {"id": "pe08", "type": "highlight"},
        {"id": "pe10", "type": "highlight"},
        {"id": "op03", "type": "highlight"},
        {"id": "cs09", "type": "highlight"},
        {"id": "te02.1", "type": "nonselectable"},
        {"id": "te02.2", "type": "nonselectable"},
        {"id": "te02.3", "type": "nonselectable"},
        {"id": "te02.4", "type": "nonselectable"},
        {"id": "cs01", "type": "nonselectable"},
        {"id": "cs02", "type": "nonselectable"},
        {"id": "cs04", "type": "nonselectable"},
        {"id": "cx03", "type": "nonselectable"},
        {"id": "cx04", "type": "nonselectable"},
        {"id": "cx07", "type": "nonselectable"},
        {"id": "cx08", "type": "nonselectable"},
        {"id": "cx09", "type": "nonselectable"},
        {"id": "op01", "type": "nonselectable"},
        {"id": "op02", "type": "nonselectable"},
        {"id": "op04", "type": "nonselectable"},
        {"id": "op05", "type": "nonselectable"},
        {"id": "op06", "type": "nonselectable"},
        {"id": "op07", "type": "nonselectable"},
        {"id": "op10", "type": "nonselectable"},
        {"id": "op12", "type": "nonselectable"},
        {"id": "op13", "type": "nonselectable"},
        {"id": "op14", "type": "nonselectable"},
        {"id": "pe01", "type": "nonselectable"},
        {"id": "pe03", "type": "nonselectable"},
        {"id": "pe06", "type": "nonselectable"},
        {"id": "pe07", "type": "nonselectable"},
        {"id": "pe09", "type": "nonselectable"},
        {"id": "pe11", "type": "nonselectable"},
        {"id": "pe12", "type": "nonselectable"},
        {"id": "pe13", "type": "nonselectable"},
        {"id": "pe14", "type": "nonselectable"},
        {"id": "te01", "type": "nonselectable"},
        {"id": "te03", "type": "nonselectable"},
        {"id": "te05", "type": "nonselectable"},
        {"id": "te07", "type": "nonselectable"},
        {"id": "te08", "type": "nonselectable"},
        {"id": "te09", "type": "nonselectable"},
        {"id": "te10", "type": "nonselectable"},
        {"id": "te11", "type": "nonselectable"},
        {"id": "te12", "type": "nonselectable"},
        {"id": "te14", "type": "nonselectable"},
        {"id": "te15", "type": "nonselectable"},
        {"id": "te17", "type": "nonselectable"}
      ]
    },      
    {
      "id": "energy",
      "title": "Energy",
      "booths": [
        {"id": "cx02", "type": "highlight"},
        {"id": "op01", "type": "highlight"},
        {"id": "op10", "type": "highlight"},
        {"id": "pe11", "type": "highlight"},
        {"id": "te03", "type": "highlight"},
        {"id": "cs01", "type": "highlight"},
        {"id": "cs02", "type": "nonselectable"},
        {"id": "cs03", "type": "highlight"},
        {"id": "cs06", "type": "highlight"},
        {"id": "cs04", "type": "nonselectable"},
        {"id": "cs05", "type": "nonselectable"},
        {"id": "cs08", "type": "nonselectable"},
        {"id": "cs10", "type": "nonselectable"},
        {"id": "cs12", "type": "nonselectable"},
        {"id": "cx01", "type": "nonselectable"},
        {"id": "cx04", "type": "nonselectable"},
        {"id": "op02", "type": "nonselectable"},
        {"id": "op03", "type": "nonselectable"},
        {"id": "op04", "type": "nonselectable"},
        {"id": "op06", "type": "nonselectable"},
        {"id": "op11", "type": "nonselectable"},
        {"id": "op12", "type": "nonselectable"},
        {"id": "op13", "type": "nonselectable"},
        {"id": "pe01", "type": "nonselectable"},
        {"id": "pe03", "type": "nonselectable"},
        {"id": "pe04", "type": "nonselectable"},
        {"id": "pe06", "type": "nonselectable"},
        {"id": "pe07", "type": "nonselectable"},
        {"id": "pe08", "type": "nonselectable"},
        {"id": "pe09", "type": "nonselectable"},
        {"id": "pe10", "type": "nonselectable"},
        {"id": "pe12", "type": "nonselectable"},
        {"id": "pe13", "type": "nonselectable"},
        {"id": "pe14", "type": "nonselectable"},
        {"id": "te01", "type": "nonselectable"},
        {"id": "te02.1", "type": "nonselectable"},
        {"id": "te02.2", "type": "nonselectable"},
        {"id": "te02.3", "type": "nonselectable"},
        {"id": "te02.4", "type": "nonselectable"},
        {"id": "te04", "type": "nonselectable"},
        {"id": "te05", "type": "nonselectable"},
        {"id": "te06", "type": "nonselectable"},
        {"id": "te07", "type": "nonselectable"},
        {"id": "te08", "type": "nonselectable"},
        {"id": "te09", "type": "nonselectable"},
        {"id": "te12", "type": "nonselectable"},
        {"id": "te14", "type": "nonselectable"},
        {"id": "te15", "type": "nonselectable"},
        {"id": "te16", "type": "nonselectable"},
        {"id": "te17", "type": "nonselectable"},
        {"id": "te18", "type": "nonselectable"}
      ]
    },      
    {
      "id": "financial",
      "title": "Financial Institutions",
      "booths": [
        {"id": "cx05", "type": "highlight"},
        {"id": "cx06", "type": "highlight"},
        {"id": "op08", "type": "highlight"},
        {"id": "pe03", "type": "highlight"},
        {"id": "pe05", "type": "highlight"},
        {"id": "pe10", "type": "highlight"},
        {"id": "te11", "type": "highlight"},
        {"id": "cs02", "type": "highlight"},
        {"id": "cs06", "type": "highlight"},
        {"id": "cs07", "type": "highlight"},
        {"id": "cs12", "type": "nonselectable"},
        {"id": "cx02", "type": "nonselectable"},
        {"id": "cx03", "type": "nonselectable"},
        {"id": "cx04", "type": "nonselectable"},
        {"id": "cx08", "type": "nonselectable"},
        {"id": "op01", "type": "nonselectable"},
        {"id": "op02", "type": "nonselectable"},
        {"id": "op04", "type": "nonselectable"},
        {"id": "pe01", "type": "nonselectable"},
        {"id": "pe04", "type": "nonselectable"},
        {"id": "pe06", "type": "nonselectable"},
        {"id": "pe07", "type": "nonselectable"},
        {"id": "pe08", "type": "nonselectable"},
        {"id": "pe09", "type": "nonselectable"},
        {"id": "pe11", "type": "nonselectable"},
        {"id": "pe12", "type": "nonselectable"},
        {"id": "pe13", "type": "nonselectable"},
        {"id": "pe14", "type": "nonselectable"},
        {"id": "te01", "type": "nonselectable"},
        {"id": "te02.1", "type": "nonselectable"},
        {"id": "te02.2", "type": "nonselectable"},
        {"id": "te02.3", "type": "nonselectable"},
        {"id": "te02.4", "type": "nonselectable"},
        {"id": "te03", "type": "nonselectable"},
        {"id": "te04", "type": "nonselectable"},
        {"id": "te05", "type": "nonselectable"},
        {"id": "te06", "type": "nonselectable"},
        {"id": "te07", "type": "nonselectable"},
        {"id": "te08", "type": "nonselectable"},
        {"id": "te09", "type": "nonselectable"},
        {"id": "te10", "type": "nonselectable"},
        {"id": "te12", "type": "nonselectable"},
        {"id": "te14", "type": "nonselectable"},
        {"id": "te15", "type": "nonselectable"},
        {"id": "te17", "type": "nonselectable"}
      ]
    },      
    {
      "id": "health",
      "title": "Health Care",
      "booths": [
        {"id": "cx01", "type": "highlight"},
        {"id": "cx05", "type": "highlight"},
        {"id": "cx06", "type": "highlight"},
        {"id": "op05", "type": "highlight"},
        {"id": "op07", "type": "highlight"},
        {"id": "op08", "type": "highlight"},
        {"id": "op09", "type": "highlight"},
        {"id": "op11", "type": "highlight"},
        {"id": "pe06", "type": "highlight"},
        {"id": "te04", "type": "highlight"},
        {"id": "te05", "type": "highlight"},
        {"id": "cs05", "type": "highlight"},
        {"id": "cs04", "type": "nonselectable"},
        {"id": "cx02", "type": "nonselectable"},
        {"id": "cx03", "type": "nonselectable"},
        {"id": "cx04", "type": "nonselectable"},
        {"id": "cx07", "type": "nonselectable"},
        {"id": "cx08", "type": "nonselectable"},
        {"id": "cx09", "type": "nonselectable"},
        {"id": "op01", "type": "nonselectable"},
        {"id": "op02", "type": "nonselectable"},
        {"id": "op03", "type": "nonselectable"},
        {"id": "op04", "type": "nonselectable"},
        {"id": "op10", "type": "nonselectable"},
        {"id": "op12", "type": "nonselectable"},
        {"id": "pe01", "type": "nonselectable"},
        {"id": "pe03", "type": "nonselectable"},
        {"id": "pe04", "type": "nonselectable"},
        {"id": "pe07", "type": "nonselectable"},
        {"id": "pe08", "type": "nonselectable"},
        {"id": "pe09", "type": "nonselectable"},
        {"id": "pe10", "type": "nonselectable"},
        {"id": "pe11", "type": "nonselectable"},
        {"id": "pe12", "type": "nonselectable"},
        {"id": "pe13", "type": "nonselectable"},
        {"id": "pe14", "type": "nonselectable"},
        {"id": "te01", "type": "nonselectable"},
        {"id": "te02.1", "type": "nonselectable"},
        {"id": "te02.2", "type": "nonselectable"},
        {"id": "te02.3", "type": "nonselectable"},
        {"id": "te02.4", "type": "nonselectable"},
        {"id": "te03", "type": "nonselectable"},
        {"id": "te06", "type": "nonselectable"},
        {"id": "te07", "type": "nonselectable"},
        {"id": "te08", "type": "nonselectable"},
        {"id": "te09", "type": "nonselectable"},
        {"id": "te12", "type": "nonselectable"},
        {"id": "te14", "type": "nonselectable"},
        {"id": "te15", "type": "nonselectable"},
        {"id": "te17", "type": "nonselectable"}
      ]
    },      
    {
      "id": "industrial",
      "title": "Industrial Goods",
      "booths": [
        {"id": "cx02", "type": "highlight"},
        {"id": "op03", "type": "highlight"},
        {"id": "op05", "type": "highlight"},
        {"id": "op07", "type": "highlight"},
        {"id": "op10", "type": "highlight"},
        {"id": "pe03", "type": "highlight"},
        {"id": "pe04", "type": "highlight"},
        {"id": "pe11", "type": "highlight"},
        {"id": "te01", "type": "highlight"},
        {"id": "cs03", "type": "highlight"},
        {"id": "cs04", "type": "highlight"},
        {"id": "cs09", "type": "highlight"},
        {"id": "cs01", "type": "nonselectable"},
        {"id": "cs02", "type": "nonselectable"},
        {"id": "cs05", "type": "nonselectable"},
        {"id": "cs10", "type": "nonselectable"},
        {"id": "cs11", "type": "nonselectable"},
        {"id": "cs12", "type": "nonselectable"},
        {"id": "cs13", "type": "nonselectable"},
        {"id": "cx01", "type": "nonselectable"},
        {"id": "cx04", "type": "nonselectable"},
        {"id": "cx05", "type": "nonselectable"},
        {"id": "op01", "type": "nonselectable"},
        {"id": "op02", "type": "nonselectable"},
        {"id": "op04", "type": "nonselectable"},
        {"id": "op06", "type": "nonselectable"},
        {"id": "op08", "type": "nonselectable"},
        {"id": "op11", "type": "nonselectable"},
        {"id": "op12", "type": "nonselectable"},
        {"id": "op13", "type": "nonselectable"},
        {"id": "op14", "type": "nonselectable"},
        {"id": "pe01", "type": "nonselectable"},
        {"id": "pe06", "type": "nonselectable"},
        {"id": "pe07", "type": "nonselectable"},
        {"id": "pe08", "type": "nonselectable"},
        {"id": "pe09", "type": "nonselectable"},
        {"id": "pe10", "type": "nonselectable"},
        {"id": "pe12", "type": "nonselectable"},
        {"id": "pe13", "type": "nonselectable"},
        {"id": "pe14", "type": "nonselectable"},
        {"id": "te02.1", "type": "nonselectable"},
        {"id": "te02.2", "type": "nonselectable"},
        {"id": "te02.3", "type": "nonselectable"},
        {"id": "te02.4", "type": "nonselectable"},
        {"id": "te03", "type": "nonselectable"},
        {"id": "te04", "type": "nonselectable"},
        {"id": "te05", "type": "nonselectable"},
        {"id": "te06", "type": "nonselectable"},
        {"id": "te07", "type": "nonselectable"},
        {"id": "te08", "type": "nonselectable"},
        {"id": "te09", "type": "nonselectable"},
        {"id": "te12", "type": "nonselectable"},
        {"id": "te14", "type": "nonselectable"},
        {"id": "te15", "type": "nonselectable"},
        {"id": "te16", "type": "nonselectable"},
        {"id": "te17", "type": "nonselectable"},
        {"id": "te18", "type": "nonselectable"}
      ]
    },      
    {
      "id": "insurance",
      "title": "Insurance",
      "booths": [
        {"id": "cx01", "type": "highlight"},
        {"id": "cx03", "type": "highlight"},
        {"id": "cx05", "type": "highlight"},
        {"id": "op01", "type": "highlight"},
        {"id": "op02", "type": "highlight"},
        {"id": "pe05", "type": "highlight"},
        {"id": "pe06", "type": "highlight"},
        {"id": "pe10", "type": "highlight"},
        {"id": "te12", "type": "highlight"},
        {"id": "cs06", "type": "highlight"},
        {"id": "cs08", "type": "highlight"},
        {"id": "cx04", "type": "nonselectable"},
        {"id": "cx06", "type": "nonselectable"},
        {"id": "cx08", "type": "nonselectable"},
        {"id": "op04", "type": "nonselectable"},
        {"id": "op08", "type": "nonselectable"},
        {"id": "pe01", "type": "nonselectable"},
        {"id": "pe03", "type": "nonselectable"},
        {"id": "pe04", "type": "nonselectable"},
        {"id": "pe07", "type": "nonselectable"},
        {"id": "pe08", "type": "nonselectable"},
        {"id": "pe09", "type": "nonselectable"},
        {"id": "pe11", "type": "nonselectable"},
        {"id": "pe12", "type": "nonselectable"},
        {"id": "pe13", "type": "nonselectable"},
        {"id": "pe14", "type": "nonselectable"},
        {"id": "te01", "type": "nonselectable"},
        {"id": "te02.1", "type": "nonselectable"},
        {"id": "te02.2", "type": "nonselectable"},
        {"id": "te02.3", "type": "nonselectable"},
        {"id": "te02.4", "type": "nonselectable"},
        {"id": "te03", "type": "nonselectable"},
        {"id": "te04", "type": "nonselectable"},
        {"id": "te05", "type": "nonselectable"},
        {"id": "te06", "type": "nonselectable"},
        {"id": "te07", "type": "nonselectable"},
        {"id": "te08", "type": "nonselectable"},
        {"id": "te09", "type": "nonselectable"},
        {"id": "te10", "type": "nonselectable"},
        {"id": "te11", "type": "nonselectable"},
        {"id": "te14", "type": "nonselectable"},
        {"id": "te15", "type": "nonselectable"},
        {"id": "te17", "type": "nonselectable"},
        {"id": "te18", "type": "nonselectable"}
      ]
    },      
    {
      "id": "public",
      "title": "Public Sector",
      "booths": [
        {"id": "cx03", "type": "highlight"},
        {"id": "op03", "type": "highlight"},
        {"id": "op10", "type": "highlight"},
        {"id": "pe06", "type": "highlight"},
        {"id": "pe08", "type": "highlight"},
        {"id": "pe10", "type": "highlight"},
        {"id": "pe11", "type": "highlight"},
        {"id": "te07", "type": "highlight"},
        {"id": "cs05", "type": "highlight"},
        {"id": "cs08", "type": "highlight"},
        {"id": "cs02", "type": "nonselectable"},
        {"id": "cs04", "type": "nonselectable"},
        {"id": "cs06", "type": "nonselectable"},
        {"id": "cs10", "type": "nonselectable"},
        {"id": "cs11", "type": "nonselectable"},
        {"id": "cs12", "type": "nonselectable"},
        {"id": "cs13", "type": "nonselectable"},
        {"id": "cx02", "type": "nonselectable"},
        {"id": "cx04", "type": "nonselectable"},
        {"id": "op01", "type": "nonselectable"},
        {"id": "op02", "type": "nonselectable"},
        {"id": "op04", "type": "nonselectable"},
        {"id": "op11", "type": "nonselectable"},
        {"id": "op12", "type": "nonselectable"},
        {"id": "op13", "type": "nonselectable"},
        {"id": "op14", "type": "nonselectable"},
        {"id": "pe01", "type": "nonselectable"},
        {"id": "pe03", "type": "nonselectable"},
        {"id": "pe04", "type": "nonselectable"},
        {"id": "pe07", "type": "nonselectable"},
        {"id": "pe09", "type": "nonselectable"},
        {"id": "pe12", "type": "nonselectable"},
        {"id": "pe13", "type": "nonselectable"},
        {"id": "pe14", "type": "nonselectable"},
        {"id": "te01", "type": "nonselectable"},
        {"id": "te02.1", "type": "nonselectable"},
        {"id": "te02.2", "type": "nonselectable"},
        {"id": "te02.3", "type": "nonselectable"},
        {"id": "te02.4", "type": "nonselectable"},
        {"id": "te03", "type": "nonselectable"},
        {"id": "te04", "type": "nonselectable"},
        {"id": "te05", "type": "nonselectable"},
        {"id": "te06", "type": "nonselectable"},
        {"id": "te08", "type": "nonselectable"},
        {"id": "te09", "type": "nonselectable"},
        {"id": "te12", "type": "nonselectable"},
        {"id": "te14", "type": "nonselectable"},
        {"id": "te15", "type": "nonselectable"},
        {"id": "te16", "type": "nonselectable"},
        {"id": "te17", "type": "nonselectable"},
        {"id": "te18", "type": "nonselectable"}
      ]
    },      
    {
      "id": "tech",
      "title": "Tech, Media & Telecom",
      "booths": [
        {"id": "cx03", "type": "highlight"},
        {"id": "cx04", "type": "highlight"},
        {"id": "cx05", "type": "highlight"},
        {"id": "op02", "type": "highlight"},
        {"id": "op04", "type": "highlight"},
        {"id": "op08", "type": "highlight"},
        {"id": "pe05", "type": "highlight"},
        {"id": "pe12", "type": "highlight"},
        {"id": "te06", "type": "highlight"},
        {"id": "te08", "type": "highlight"},
        {"id": "te09", "type": "highlight"},
        {"id": "te12", "type": "highlight"},
        {"id": "cs08", "type": "highlight"},
        {"id": "cs12", "type": "nonselectable"},
        {"id": "cx02", "type": "nonselectable"},
        {"id": "cx06", "type": "nonselectable"},
        {"id": "cx07", "type": "nonselectable"},
        {"id": "cx08", "type": "nonselectable"},
        {"id": "cx09", "type": "nonselectable"},
        {"id": "op01", "type": "nonselectable"},
        {"id": "op10", "type": "nonselectable"},
        {"id": "op12", "type": "nonselectable"},
        {"id": "pe01", "type": "nonselectable"},
        {"id": "pe03", "type": "nonselectable"},
        {"id": "pe04", "type": "nonselectable"},
        {"id": "pe06", "type": "nonselectable"},
        {"id": "pe07", "type": "nonselectable"},
        {"id": "pe08", "type": "nonselectable"},
        {"id": "pe09", "type": "nonselectable"},
        {"id": "pe10", "type": "nonselectable"},
        {"id": "pe11", "type": "nonselectable"},
        {"id": "pe12", "type": "nonselectable"},
        {"id": "pe13", "type": "nonselectable"},
        {"id": "pe14", "type": "nonselectable"},
        {"id": "te01", "type": "nonselectable"},
        {"id": "te02.1", "type": "nonselectable"},
        {"id": "te02.2", "type": "nonselectable"},
        {"id": "te02.3", "type": "nonselectable"},
        {"id": "te02.4", "type": "nonselectable"},
        {"id": "te03", "type": "nonselectable"},
        {"id": "te04", "type": "nonselectable"},
        {"id": "te05", "type": "nonselectable"},
        {"id": "te07", "type": "nonselectable"},
        {"id": "te10", "type": "nonselectable"},
        {"id": "te14", "type": "nonselectable"},
        {"id": "te15", "type": "nonselectable"},
        {"id": "te17", "type": "nonselectable"}
      ]
    },      
    {
      "id": "travel",
      "title": "Travel, Cities & Infrastructure",
      "booths": [
        {"id": "cx02", "type": "highlight"},
        {"id": "cx03", "type": "highlight"},
        {"id": "op05", "type": "highlight"},
        {"id": "op07", "type": "highlight"},
        {"id": "op08", "type": "highlight"},
        {"id": "pe03", "type": "highlight"},
        {"id": "te07", "type": "highlight"},
        {"id": "te12", "type": "highlight"},
        {"id": "cs03", "type": "highlight"},
        {"id": "cs06", "type": "highlight"},
        {"id": "cs08", "type": "highlight"},
        {"id": "cs05", "type": "nonselectable"},
        {"id": "cs10", "type": "nonselectable"},
        {"id": "cs11", "type": "nonselectable"},
        {"id": "cs12", "type": "nonselectable"},
        {"id": "cs13", "type": "nonselectable"},
        {"id": "cx01", "type": "nonselectable"},
        {"id": "cx04", "type": "nonselectable"},
        {"id": "cx05", "type": "nonselectable"},
        {"id": "cx06", "type": "nonselectable"},
        {"id": "cx07", "type": "nonselectable"},
        {"id": "cx09", "type": "nonselectable"},
        {"id": "op01", "type": "nonselectable"},
        {"id": "op02", "type": "nonselectable"},
        {"id": "op04", "type": "nonselectable"},
        {"id": "op06", "type": "nonselectable"},
        {"id": "pe01", "type": "nonselectable"},
        {"id": "pe04", "type": "nonselectable"},
        {"id": "pe06", "type": "nonselectable"},
        {"id": "pe07", "type": "nonselectable"},
        {"id": "pe08", "type": "nonselectable"},
        {"id": "pe09", "type": "nonselectable"},
        {"id": "pe10", "type": "nonselectable"},
        {"id": "pe11", "type": "nonselectable"},
        {"id": "pe12", "type": "nonselectable"},
        {"id": "pe13", "type": "nonselectable"},
        {"id": "pe14", "type": "nonselectable"},
        {"id": "te01", "type": "nonselectable"},
        {"id": "te02.1", "type": "nonselectable"},
        {"id": "te02.2", "type": "nonselectable"},
        {"id": "te02.3", "type": "nonselectable"},
        {"id": "te02.4", "type": "nonselectable"},
        {"id": "te03", "type": "nonselectable"},
        {"id": "te04", "type": "nonselectable"},
        {"id": "te05", "type": "nonselectable"},
        {"id": "te06", "type": "nonselectable"},
        {"id": "te08", "type": "nonselectable"},
        {"id": "te09", "type": "nonselectable"},
        {"id": "te10", "type": "nonselectable"},
        {"id": "te11", "type": "nonselectable"},
        {"id": "te14", "type": "nonselectable"},
        {"id": "te15", "type": "nonselectable"},
        {"id": "te16", "type": "nonselectable"},
        {"id": "te17", "type": "nonselectable"},
        {"id": "te18", "type": "nonselectable"}
      ]
    },
    {
      "id": "collaborators",
      "title": "Partners & Collaborators",
      "booths": [
        {"id": "cx04", "type": "highlight"},
        {"id": "cx07", "type": "highlight"},
        {"id": "cx09", "type": "highlight"},
        {"id": "op01", "type": "highlight"},
        {"id": "op02", "type": "highlight"},
        {"id": "op06", "type": "highlight"},
        {"id": "op08", "type": "highlight"},
        {"id": "op12", "type": "highlight"},
        {"id": "pe01", "type": "highlight"},
        {"id": "pe09", "type": "highlight"},
        {"id": "te05", "type": "highlight"},
        {"id": "te06", "type": "highlight"},
        {"id": "te08", "type": "highlight"},
        {"id": "te09", "type": "highlight"},
        {"id": "te10", "type": "highlight"},
        {"id": "te14", "type": "highlight"},
        {"id": "te15", "type": "highlight"},
        {"id": "cs05", "type": "highlight"}
      ]
    },
    {
      "id": "startups",
      "title": "Startup",
      "booths": [
        {"id": "cx08", "type": "highlight"},
        {"id": "op13", "type": "highlight"},
        {"id": "op14", "type": "highlight"},
        {"id": "pe13", "type": "highlight"},
        {"id": "pe14", "type": "highlight"},
        {"id": "te02.1", "type": "highlight"},
        {"id": "te02.2", "type": "highlight"},
        {"id": "te02.3", "type": "highlight"},
        {"id": "te02.4", "type": "highlight"},
        {"id": "te16", "type": "highlight"},
        {"id": "te17", "type": "highlight"},
        {"id": "te18", "type": "highlight"},
        {"id": "cs10", "type": "highlight"},
        {"id": "cs11", "type": "highlight"},
        {"id": "cs12", "type": "highlight"},
        {"id": "cs13", "type": "highlight"}
      ]
    }
    
  ]
}

